<?xml version="1.0" encoding="windows-1252" ?>
<!DOCTYPE ViewLink SYSTEM "jbo_03_01.dtd">
<!---->
<ViewLink
  xmlns="http://xmlns.oracle.com/bc4j"
  Name="DeptMgrFkLink"
  Version="11.1.2.64.36"
  EntityAssociation="peddi.adftutorial.demo.model.entity.DeptMgrFkAssoc">
  <ViewLinkDefEnd
    Name="EmployeesVO1_1"
    Cardinality="1"
    Source="true"
    Owner="peddi.adftutorial.demo.model.view.EmployeesVO">
    <DesignTime>
      <Attr Name="_finderName" Value="EmployeesVO1"/>
      <Attr Name="_isUpdateable" Value="true"/>
    </DesignTime>
    <AttrArray Name="Attributes">
      <Item Value="peddi.adftutorial.demo.model.view.EmployeesVO.EmployeeId"/>
    </AttrArray>
  </ViewLinkDefEnd>
  <ViewLinkDefEnd
    Name="DepartmentsVO"
    Cardinality="-1"
    Owner="peddi.adftutorial.demo.model.view.DepartmentsVO">
    <DesignTime>
      <Attr Name="_finderName" Value="DepartmentsVO"/>
      <Attr Name="_isUpdateable" Value="true"/>
    </DesignTime>
    <AttrArray Name="Attributes">
      <Item Value="peddi.adftutorial.demo.model.view.DepartmentsVO.ManagerId"/>
    </AttrArray>
  </ViewLinkDefEnd>
</ViewLink>
